sort_tracker/__init__.py
sort_tracker/sort.py
sort_tracker_py-1.0.2.dist-info/LICENSE
sort_tracker_py-1.0.2.dist-info/METADATA
sort_tracker_py-1.0.2.dist-info/WHEEL
sort_tracker_py-1.0.2.dist-info/top_level.txt
sort_tracker_py-1.0.2.dist-info/RECORD
