Metadata-Version: 2.1
Name: sort-tracker-py
Version: 1.0.2
Summary: SORT A Simple, Online and Realtime Tracker
Home-page: https://github.com/andresprados/sort
Author: Alex Bewley
Maintainer: Andres Prados Torreblanca
Maintainer-email: andresprator@gmail.com
License: GPLv3
Classifier: Programming Language :: Python :: 3
Classifier: License :: OSI Approved :: GNU General Public License v3 (GPLv3)
Classifier: Operating System :: OS Independent
Requires-Python: >=3.6
License-File: LICENSE
Requires-Dist: numpy (>=1.18.2)
Requires-Dist: scipy
Requires-Dist: filterpy (>=1.4.5)
Requires-Dist: lap (>=0.4.0)
